huaweicloudsdksts/__init__.py
huaweicloudsdksts/v1/__init__.py
huaweicloudsdksts/v1/sts_async_client.py
huaweicloudsdksts/v1/sts_client.py
huaweicloudsdksts/v1/model/__init__.py
huaweicloudsdksts/v1/model/assume_agency_req_body.py
huaweicloudsdksts/v1/model/assume_agency_request.py
huaweicloudsdksts/v1/model/assume_agency_response.py
huaweicloudsdksts/v1/model/assumed_agency_dto.py
huaweicloudsdksts/v1/model/credentials_dto.py
huaweicloudsdksts/v1/model/decode_authorization_message_req.py
huaweicloudsdksts/v1/model/decode_authorization_message_request.py
huaweicloudsdksts/v1/model/decode_authorization_message_response.py
huaweicloudsdksts/v1/model/get_caller_identity_request.py
huaweicloudsdksts/v1/model/get_caller_identity_response.py
huaweicloudsdksts/v1/model/tag_dto.py
huaweicloudsdksts/v1/model/tag_key_dto.py
huaweicloudsdksts/v1/region/__init__.py
huaweicloudsdksts/v1/region/sts_region.py
huaweicloudsdksts-3.1.184.dist-info/METADATA
huaweicloudsdksts-3.1.184.dist-info/WHEEL
huaweicloudsdksts-3.1.184.dist-info/licenses/LICENSE
huaweicloudsdksts-3.1.184.dist-info/RECORD
